numato_gpio/__init__.py
numato_gpio/__main__.py
numato_gpio/device_types.py
numato_gpio-0.14.0.dist-info/METADATA
numato_gpio-0.14.0.dist-info/WHEEL
numato_gpio-0.14.0.dist-info/entry_points.txt
numato_gpio-0.14.0.dist-info/licenses/LICENSE
numato_gpio-0.14.0.dist-info/RECORD
