Metadata-Version: 2.4
Name: numato-gpio
Version: 0.14.0
Summary: Python API for Numato GPIO Expanders
Project-URL: Homepage, https://github.com/clssn/numato-gpio
Project-URL: Repository, https://github.com/clssn/numato-gpio.git
Author-email: Henning Claßen <code@clssn.de>
License-Expression: MIT
License-File: LICENSE
Classifier: License :: OSI Approved :: MIT License
Classifier: Operating System :: POSIX :: Linux
Classifier: Programming Language :: Python :: 3.8
Classifier: Programming Language :: Python :: 3.9
Classifier: Programming Language :: Python :: 3.10
Classifier: Programming Language :: Python :: 3.11
Classifier: Programming Language :: Python :: 3.12
Classifier: Programming Language :: Python :: 3.13
Requires-Python: <3.14,>=3.9
Requires-Dist: pyserial<4,>=3.1
Requires-Dist: rich>=14.0.0
